async_helper/__init__.py
async_helper/helper.py
async_helper-0.0.3.dist-info/LICENSE
async_helper-0.0.3.dist-info/METADATA
async_helper-0.0.3.dist-info/WHEEL
async_helper-0.0.3.dist-info/top_level.txt
async_helper-0.0.3.dist-info/RECORD
