Metadata-Version: 2.1
Name: async-helper
Version: 0.0.3
Summary: A bridge between the asynchronous and synchronous world
Home-page: https://github.com/sebst/async-helper
Author: Sebastian Steins
Author-email: opensource@seb.st
License: UNKNOWN
Project-URL: Bug Tracker, https://github.com/sebst/async-helper/issues
Platform: UNKNOWN
Classifier: Programming Language :: Python :: 3
Classifier: License :: OSI Approved :: MIT License
Classifier: Operating System :: OS Independent
Requires-Python: >=3.6
